<?xml version="1.0" encoding="utf-8" ?>
<dwsync>
<file name="index.html" server="2013.auction-ruseasons.ru/public_html/" local="130041822372070000" remote="130043967600000000" />
<file name="desert_226x226.jpg" server="2013.auction-ruseasons.ru/public_html/" local="130059114881246000" remote="130059532200000000" />
<file name="hydrangeas_226x226.jpg" server="2013.auction-ruseasons.ru/public_html/" local="130059144072006000" remote="130059532200000000" />
<file name="jellyfish_226x226.jpg" server="2013.auction-ruseasons.ru/public_html/" local="130057720487942000" remote="130059532200000000" />
<file name="icon_02_213_09_24_226x226.jpg" server="2013.auction-ruseasons.ru/public_html/" local="130063784903976000" remote="130063817400000000" />
<file name="icon_02_213_09_2_226x226.jpg" server="2013.auction-ruseasons.ru/public_html/" local="130063784903986000" remote="130063817400000000" />
<file name="lighthouse_226x226.jpg" server="2013.auction-ruseasons.ru/public_html/" local="130063784904006000" remote="130063817400000000" />
<file name="02_215_03_1_226x226.jpg" server="2013.auction-ruseasons.ru/public_html/" local="130063784903436000" remote="130063817400000000" />
<file name="4463922_226x226.jpg" server="2013.auction-ruseasons.ru/public_html/" local="130064597412226000" remote="130064705400000000" />
<file name="green-flash-1_226x226.jpg" server="2013.auction-ruseasons.ru/public_html/" local="130064598625666000" remote="130064705400000000" />
<file name="green-flash-over-setting-sun-111103.jpg" server="2013.auction-ruseasons.ru/public_html/" local="130064595010876000" remote="130064705400000000" />
<file name="mongolian-basin-1600.jpg" server="2013.auction-ruseasons.ru/public_html/" local="130064594797146000" remote="130064705400000000" />
<file name="robotnaut-open-switch-cover6_226x226.jpg" server="2013.auction-ruseasons.ru/public_html/" local="130064598102506000" remote="130064705400000000" />
<file name="rudolfensis_226x226.jpg" server="2013.auction-ruseasons.ru/public_html/" local="130064597843786000" remote="130064705400000000" />
<file name="the_material_around_sn_1987a_900_226x226.png" server="2013.auction-ruseasons.ru/public_html/" local="130064598374876000" remote="130064706000000000" />
</dwsync>