<?xml version="1.0" encoding="utf-8" ?>
<dwsync>
<file name="index.html" server="2013.auction-ruseasons.ru/public_html/" local="130041827746800000" remote="130089453000000000" Dst="-1" />
<file name="mod_virtuemart_product.xml" server="2013.auction-ruseasons.ru/public_html/" local="130041827746930000" remote="130089453000000000" Dst="-1" />
<file name="helper.php" server="2013.auction-ruseasons.ru/public_html/" local="130041827746790000" remote="130089453000000000" Dst="-1" />
<file name="mod_virtuemart_product.php" server="2013.auction-ruseasons.ru/public_html/" local="130041827746920000" remote="130089453600000000" Dst="-1" />
<file name="helper.php" server="I:/auction-ruseasons/" local="130419717820350000" remote="130419717840000000" Dst="0" />
<file name="index.html" server="I:/auction-ruseasons/" local="130419717820350000" remote="130419717840000000" Dst="0" />
<file name="mod_virtuemart_product.php" server="I:/auction-ruseasons/" local="130419717820610000" remote="130419717840000000" Dst="0" />
<file name="mod_virtuemart_product.xml" server="I:/auction-ruseasons/" local="130419717820610000" remote="130419717840000000" Dst="0" />
</dwsync>