<?xml version="1.0" encoding="utf-8" ?>
<dwsync>
<file name="index.html" server="2013.auction-ruseasons.ru/public_html/" local="129967394200000000" remote="130089448200000000" Dst="-1" />
<file name="entry.php" server="2013.auction-ruseasons.ru/public_html/" local="129967394200000000" remote="130089448200000000" Dst="-1" />
<file name="log.php" server="2013.auction-ruseasons.ru/public_html/" local="129967394200000000" remote="130089448200000000" Dst="-1" />
<file name="logexception.php" server="2013.auction-ruseasons.ru/public_html/" local="129967394200000000" remote="130089448200000000" Dst="-1" />
<file name="logger.php" server="2013.auction-ruseasons.ru/public_html/" local="129967394200000000" remote="130089448200000000" Dst="-1" />
<file name="entry.php" server="I:/auction-ruseasons/" local="130419717740540000" remote="130419717760000000" Dst="0" />
<file name="index.html" server="I:/auction-ruseasons/" local="130419717740540000" remote="130419717760000000" Dst="0" />
<file name="log.php" server="I:/auction-ruseasons/" local="130419717740600000" remote="130419717760000000" Dst="0" />
<file name="logexception.php" server="I:/auction-ruseasons/" local="130419717740880000" remote="130419717760000000" Dst="0" />
<file name="logger.php" server="I:/auction-ruseasons/" local="130419717740890000" remote="130419717760000000" Dst="0" />
</dwsync>