<?xml version="1.0" encoding="utf-8" ?>
<dwsync>
<file name="index.html" server="2013.auction-ruseasons.ru/public_html/" local="130043541453840000" remote="130043557800000000" />
<file name="icon-14-acymailing.png" server="2013.auction-ruseasons.ru/public_html/" local="130043541446220000" remote="130043557800000000" />
<file name="icon-14-color-action.png" server="2013.auction-ruseasons.ru/public_html/" local="130043541446240000" remote="130043557800000000" />
<file name="icon-14-color-acypreview.png" server="2013.auction-ruseasons.ru/public_html/" local="130043541446480000" remote="130043557800000000" />
<file name="icon-14-color-bounce-rules.png" server="2013.auction-ruseasons.ru/public_html/" local="130043541446500000" remote="130043557800000000" />
<file name="icon-14-color-bounce.png" server="2013.auction-ruseasons.ru/public_html/" local="130043541446530000" remote="130043557800000000" />
<file name="icon-14-color-chart.png" server="2013.auction-ruseasons.ru/public_html/" local="130043541446550000" remote="130043557800000000" />
<file name="icon-14-color-export.png" server="2013.auction-ruseasons.ru/public_html/" local="130043541446580000" remote="130043557800000000" />
<file name="icon-14-color-generate.png" server="2013.auction-ruseasons.ru/public_html/" local="130043541446600000" remote="130043557800000000" />
<file name="icon-14-color-import.png" server="2013.auction-ruseasons.ru/public_html/" local="130043541446640000" remote="130043557800000000" />
<file name="icon-14-color-print.png" server="2013.auction-ruseasons.ru/public_html/" local="130043541446660000" remote="130043557800000000" />
<file name="icon-14-color-process.png" server="2013.auction-ruseasons.ru/public_html/" local="130043541446690000" remote="130043558400000000" />
<file name="icon-14-color-replace-tag.png" server="2013.auction-ruseasons.ru/public_html/" local="130043541446710000" remote="130043558400000000" />
<file name="icon-14-color-schedule.png" server="2013.auction-ruseasons.ru/public_html/" local="130043541446740000" remote="130043558400000000" />
<file name="icon-14-color-sendtest.png" server="2013.auction-ruseasons.ru/public_html/" local="130043541446770000" remote="130043558400000000" />
<file name="icon-14-color-spamtest.png" server="2013.auction-ruseasons.ru/public_html/" local="130043541446790000" remote="130043558400000000" />
<file name="icon-14-color-tag.png" server="2013.auction-ruseasons.ru/public_html/" local="130043541446810000" remote="130043558400000000" />
<file name="icon-14-color-template.png" server="2013.auction-ruseasons.ru/public_html/" local="130043541447120000" remote="130043558400000000" />
<file name="icon-14-color-unschedule.png" server="2013.auction-ruseasons.ru/public_html/" local="130043541447150000" remote="130043558400000000" />
<file name="icon-16-acyconfig.png" server="2013.auction-ruseasons.ru/public_html/" local="130043541447180000" remote="130043558400000000" />
<file name="icon-16-acyexport.png" server="2013.auction-ruseasons.ru/public_html/" local="130043541447200000" remote="130043558400000000" />
<file name="icon-16-acylist.png" server="2013.auction-ruseasons.ru/public_html/" local="130043541447340000" remote="130043558400000000" />
<file name="icon-16-acymailing.png" server="2013.auction-ruseasons.ru/public_html/" local="130043541447360000" remote="130043558400000000" />
<file name="icon-16-acynew.png" server="2013.auction-ruseasons.ru/public_html/" local="130043541447390000" remote="130043558400000000" />
<file name="icon-16-acytemplate.png" server="2013.auction-ruseasons.ru/public_html/" local="130043541447410000" remote="130043558400000000" />
<file name="icon-16-add.png" server="2013.auction-ruseasons.ru/public_html/" local="130043541447530000" remote="130043558400000000" />
<file name="icon-16-autonewsletter.png" server="2013.auction-ruseasons.ru/public_html/" local="130043541447560000" remote="130043558400000000" />
<file name="icon-16-bounces.png" server="2013.auction-ruseasons.ru/public_html/" local="130043541447580000" remote="130043558400000000" />
<file name="icon-16-campaign.png" server="2013.auction-ruseasons.ru/public_html/" local="130043541447600000" remote="130043558400000000" />
<file name="icon-16-edit.png" server="2013.auction-ruseasons.ru/public_html/" local="130043541447760000" remote="130043558400000000" />
<file name="icon-16-fields.png" server="2013.auction-ruseasons.ru/public_html/" local="130043541447790000" remote="130043558400000000" />
<file name="icon-16-filter.png" server="2013.auction-ruseasons.ru/public_html/" local="130043541447810000" remote="130043558400000000" />
<file name="icon-16-import.png" server="2013.auction-ruseasons.ru/public_html/" local="130043541447830000" remote="130043558400000000" />
<file name="icon-16-newsletter.png" server="2013.auction-ruseasons.ru/public_html/" local="130043541448090000" remote="130043558400000000" />
<file name="icon-16-process.png" server="2013.auction-ruseasons.ru/public_html/" local="130043541448110000" remote="130043558400000000" />
<file name="icon-16-refuse.png" server="2013.auction-ruseasons.ru/public_html/" local="130043541448300000" remote="130043558400000000" />
<file name="icon-16-stats.png" server="2013.auction-ruseasons.ru/public_html/" local="130043541448330000" remote="130043558400000000" />
<file name="icon-16-update.png" server="2013.auction-ruseasons.ru/public_html/" local="130043541449010000" remote="130043558400000000" />
<file name="icon-16-users.png" server="2013.auction-ruseasons.ru/public_html/" local="130043541449030000" remote="130043558400000000" />
<file name="icon-32-acyaction.png" server="2013.auction-ruseasons.ru/public_html/" local="130043541449050000" remote="130043558400000000" />
<file name="icon-32-acyexport.png" server="2013.auction-ruseasons.ru/public_html/" local="130043541449090000" remote="130043558400000000" />
<file name="icon-32-acylist.png" server="2013.auction-ruseasons.ru/public_html/" local="130043541449840000" remote="130043558400000000" />
<file name="icon-32-acymailing.png" server="2013.auction-ruseasons.ru/public_html/" local="130043541449880000" remote="130043558400000000" />
<file name="icon-32-acypreview.png" server="2013.auction-ruseasons.ru/public_html/" local="130043541449900000" remote="130043558400000000" />
<file name="icon-32-acyprint.png" server="2013.auction-ruseasons.ru/public_html/" local="130043541449920000" remote="130043558400000000" />
<file name="icon-32-acysend.png" server="2013.auction-ruseasons.ru/public_html/" local="130043541450830000" remote="130043558400000000" />
<file name="icon-32-acytemplate.png" server="2013.auction-ruseasons.ru/public_html/" local="130043541451860000" remote="130043558400000000" />
<file name="icon-32-apply.png" server="2013.auction-ruseasons.ru/public_html/" local="130043541451890000" remote="130043558400000000" />
<file name="icon-32-bounces.png" server="2013.auction-ruseasons.ru/public_html/" local="130043541451910000" remote="130043558400000000" />
<file name="icon-32-cancel.png" server="2013.auction-ruseasons.ru/public_html/" local="130043541452030000" remote="130043558400000000" />
<file name="icon-32-delete.png" server="2013.auction-ruseasons.ru/public_html/" local="130043541452050000" remote="130043558400000000" />
<file name="icon-32-edit.png" server="2013.auction-ruseasons.ru/public_html/" local="130043541452080000" remote="130043558400000000" />
<file name="icon-32-fields.png" server="2013.auction-ruseasons.ru/public_html/" local="130043541452100000" remote="130043558400000000" />
<file name="icon-32-filter.png" server="2013.auction-ruseasons.ru/public_html/" local="130043541452220000" remote="130043558400000000" />
<file name="icon-32-help.png" server="2013.auction-ruseasons.ru/public_html/" local="130043541452250000" remote="130043558400000000" />
<file name="icon-32-import.png" server="2013.auction-ruseasons.ru/public_html/" local="130043541452280000" remote="130043558400000000" />
<file name="icon-32-installbounces.png" server="2013.auction-ruseasons.ru/public_html/" local="130043541452300000" remote="130043558400000000" />
<file name="icon-32-loadfilter.png" server="2013.auction-ruseasons.ru/public_html/" local="130043541452480000" remote="130043558400000000" />
<file name="icon-32-new.png" server="2013.auction-ruseasons.ru/public_html/" local="130043541452510000" remote="130043558400000000" />
<file name="icon-32-process.png" server="2013.auction-ruseasons.ru/public_html/" local="130043541452540000" remote="130043558400000000" />
<file name="icon-32-replacetag.png" server="2013.auction-ruseasons.ru/public_html/" local="130043541452560000" remote="130043558400000000" />
<file name="icon-32-save.png" server="2013.auction-ruseasons.ru/public_html/" local="130043541452660000" remote="130043558400000000" />
<file name="icon-32-schedule.png" server="2013.auction-ruseasons.ru/public_html/" local="130043541452690000" remote="130043558400000000" />
<file name="icon-32-share.png" server="2013.auction-ruseasons.ru/public_html/" local="130043541452840000" remote="130043558400000000" />
<file name="icon-32-spamtest.png" server="2013.auction-ruseasons.ru/public_html/" local="130043541452930000" remote="130043558400000000" />
<file name="icon-32-stats.png" server="2013.auction-ruseasons.ru/public_html/" local="130043541452950000" remote="130043558400000000" />
<file name="icon-32-tag.png" server="2013.auction-ruseasons.ru/public_html/" local="130043541452980000" remote="130043558400000000" />
<file name="icon-32-unschedule.png" server="2013.auction-ruseasons.ru/public_html/" local="130043541453000000" remote="130043558400000000" />
<file name="icon-48-acyaction.png" server="2013.auction-ruseasons.ru/public_html/" local="130043541453030000" remote="130043558400000000" />
<file name="icon-48-acyconfig.png" server="2013.auction-ruseasons.ru/public_html/" local="130043541453050000" remote="130043558400000000" />
<file name="icon-48-acyexport.png" server="2013.auction-ruseasons.ru/public_html/" local="130043541453070000" remote="130043558400000000" />
<file name="icon-48-acylist.png" server="2013.auction-ruseasons.ru/public_html/" local="130043541453100000" remote="130043558400000000" />
<file name="icon-48-acymailing.png" server="2013.auction-ruseasons.ru/public_html/" local="130043541453120000" remote="130043558400000000" />
<file name="icon-48-acytemplate.png" server="2013.auction-ruseasons.ru/public_html/" local="130043541453420000" remote="130043558400000000" />
<file name="icon-48-acyupdate.png" server="2013.auction-ruseasons.ru/public_html/" local="130043541453460000" remote="130043559000000000" />
<file name="icon-48-acyusers.png" server="2013.auction-ruseasons.ru/public_html/" local="130043541453490000" remote="130043559000000000" />
<file name="icon-48-autonewsletter.png" server="2013.auction-ruseasons.ru/public_html/" local="130043541453520000" remote="130043559000000000" />
<file name="icon-48-bounces.png" server="2013.auction-ruseasons.ru/public_html/" local="130043541453570000" remote="130043559000000000" />
<file name="icon-48-campaign.png" server="2013.auction-ruseasons.ru/public_html/" local="130043541453600000" remote="130043559000000000" />
<file name="icon-48-fields.png" server="2013.auction-ruseasons.ru/public_html/" local="130043541453620000" remote="130043559000000000" />
<file name="icon-48-filter.png" server="2013.auction-ruseasons.ru/public_html/" local="130043541453640000" remote="130043559000000000" />
<file name="icon-48-import.png" server="2013.auction-ruseasons.ru/public_html/" local="130043541453670000" remote="130043559000000000" />
<file name="icon-48-newsletter.png" server="2013.auction-ruseasons.ru/public_html/" local="130043541453700000" remote="130043559000000000" />
<file name="icon-48-process.png" server="2013.auction-ruseasons.ru/public_html/" local="130043541453720000" remote="130043559000000000" />
<file name="icon-48-schedule.png" server="2013.auction-ruseasons.ru/public_html/" local="130043541453740000" remote="130043559000000000" />
<file name="icon-48-share.png" server="2013.auction-ruseasons.ru/public_html/" local="130043541453770000" remote="130043559000000000" />
<file name="icon-48-stats.png" server="2013.auction-ruseasons.ru/public_html/" local="130043541453800000" remote="130043559000000000" />
<file name="icon-48-unschedule.png" server="2013.auction-ruseasons.ru/public_html/" local="130043541453820000" remote="130043559000000000" />
</dwsync>