<?xml version="1.0" encoding="utf-8" ?>
<dwsync>
<file name="120px_pinnacles_western_australia.jpg" server="I:/auction-ruseasons/" local="130419717640830000" remote="130419717660000000" Dst="0" />
<file name="120px_rainforest_bluemountainsnsw.jpg" server="I:/auction-ruseasons/" local="130419717640840000" remote="130419717660000000" Dst="0" />
<file name="180px_ormiston_pound.jpg" server="I:/auction-ruseasons/" local="130419717640850000" remote="130419717660000000" Dst="0" />
<file name="250px_cradle_mountain_seen_from_barn_bluff.jpg" server="I:/auction-ruseasons/" local="130419717640870000" remote="130419717660000000" Dst="0" />
<file name="727px_rainforest_bluemountainsnsw.jpg" server="I:/auction-ruseasons/" local="130419717640920000" remote="130419717660000000" Dst="0" />
<file name="800px_cradle_mountain_seen_from_barn_bluff.jpg" server="I:/auction-ruseasons/" local="130419717640930000" remote="130419717660000000" Dst="0" />
<file name="800px_ormiston_pound.jpg" server="I:/auction-ruseasons/" local="130419717640940000" remote="130419717660000000" Dst="0" />
<file name="800px_pinnacles_western_australia.jpg" server="I:/auction-ruseasons/" local="130419717640960000" remote="130419717660000000" Dst="0" />
<file name="index.html" server="I:/auction-ruseasons/" local="130419717640970000" remote="130419717660000000" Dst="0" />
</dwsync>