<?xml version="1.0" encoding="utf-8" ?>
<dwsync>
<file name="en-GB.com_admin.ini" server="77.222.40.220/2013/public_html/" local="130113936000000000" remote="130113936000000000" Dst="0" />
<file name="en-GB.com_admin.sys.ini" server="77.222.40.220/2013/public_html/" local="130113936000000000" remote="130113936000000000" Dst="0" />
<file name="en-GB.com_banners.ini" server="77.222.40.220/2013/public_html/" local="130113936000000000" remote="130113936000000000" Dst="0" />
<file name="en-GB.com_banners.sys.ini" server="77.222.40.220/2013/public_html/" local="130113936000000000" remote="130113936000000000" Dst="0" />
<file name="en-GB.com_cache.ini" server="77.222.40.220/2013/public_html/" local="130113936000000000" remote="130113936000000000" Dst="0" />
<file name="en-GB.com_cache.sys.ini" server="77.222.40.220/2013/public_html/" local="130113936000000000" remote="130113936000000000" Dst="0" />
<file name="en-GB.com_categories.ini" server="77.222.40.220/2013/public_html/" local="130113936000000000" remote="130113936000000000" Dst="0" />
<file name="en-GB.com_categories.sys.ini" server="77.222.40.220/2013/public_html/" local="130113936000000000" remote="130113936000000000" Dst="0" />
<file name="en-GB.com_checkin.ini" server="77.222.40.220/2013/public_html/" local="130113936000000000" remote="130113936000000000" Dst="0" />
<file name="en-GB.com_checkin.sys.ini" server="77.222.40.220/2013/public_html/" local="130113936000000000" remote="130113936000000000" Dst="0" />
<file name="en-GB.com_config.ini" server="77.222.40.220/2013/public_html/" local="130113936000000000" remote="130113936000000000" Dst="0" />
<file name="en-GB.com_config.sys.ini" server="77.222.40.220/2013/public_html/" local="130113936000000000" remote="130113936000000000" Dst="0" />
<file name="en-GB.com_contact.ini" server="77.222.40.220/2013/public_html/" local="130113936000000000" remote="130113936000000000" Dst="0" />
<file name="en-GB.com_contact.sys.ini" server="77.222.40.220/2013/public_html/" local="130113936000000000" remote="130113936000000000" Dst="0" />
<file name="en-GB.com_content.ini" server="77.222.40.220/2013/public_html/" local="130113936000000000" remote="130113936000000000" Dst="0" />
<file name="en-GB.com_content.sys.ini" server="77.222.40.220/2013/public_html/" local="130113936000000000" remote="130113936000000000" Dst="0" />
<file name="en-GB.com_cpanel.ini" server="77.222.40.220/2013/public_html/" local="130113936000000000" remote="130113936000000000" Dst="0" />
<file name="en-GB.com_cpanel.sys.ini" server="77.222.40.220/2013/public_html/" local="130113936000000000" remote="130113936000000000" Dst="0" />
<file name="en-GB.com_finder.ini" server="77.222.40.220/2013/public_html/" local="130113936000000000" remote="130113936000000000" Dst="0" />
<file name="en-GB.com_finder.sys.ini" server="77.222.40.220/2013/public_html/" local="130113936000000000" remote="130113936000000000" Dst="0" />
<file name="en-GB.com_installer.ini" server="77.222.40.220/2013/public_html/" local="130113936000000000" remote="130113936000000000" Dst="0" />
<file name="en-GB.com_installer.sys.ini" server="77.222.40.220/2013/public_html/" local="130113936000000000" remote="130113936000000000" Dst="0" />
<file name="en-GB.com_jce.ini" server="77.222.40.220/2013/public_html/" local="130043088000000000" remote="130043088000000000" Dst="0" />
<file name="en-GB.com_jce.sys.ini" server="77.222.40.220/2013/public_html/" local="130043088000000000" remote="130043088000000000" Dst="0" />
<file name="en-GB.com_joomlaupdate.ini" server="77.222.40.220/2013/public_html/" local="130113936000000000" remote="130113936000000000" Dst="0" />
<file name="en-GB.com_joomlaupdate.sys.ini" server="77.222.40.220/2013/public_html/" local="130113936000000000" remote="130113936000000000" Dst="0" />
<file name="en-GB.com_languages.ini" server="77.222.40.220/2013/public_html/" local="130113936000000000" remote="130113936000000000" Dst="0" />
<file name="en-GB.com_languages.sys.ini" server="77.222.40.220/2013/public_html/" local="130113936000000000" remote="130113936000000000" Dst="0" />
<file name="en-GB.com_login.ini" server="77.222.40.220/2013/public_html/" local="130113936000000000" remote="130113936000000000" Dst="0" />
<file name="en-GB.com_login.sys.ini" server="77.222.40.220/2013/public_html/" local="130113936000000000" remote="130113936000000000" Dst="0" />
<file name="en-GB.com_mailto.sys.ini" server="77.222.40.220/2013/public_html/" local="130113936000000000" remote="130113936000000000" Dst="0" />
<file name="en-GB.com_media.ini" server="77.222.40.220/2013/public_html/" local="130113936000000000" remote="130113936000000000" Dst="0" />
<file name="en-GB.com_media.sys.ini" server="77.222.40.220/2013/public_html/" local="130113936000000000" remote="130113936000000000" Dst="0" />
<file name="en-GB.com_menus.ini" server="77.222.40.220/2013/public_html/" local="130113936000000000" remote="130113936000000000" Dst="0" />
<file name="en-GB.com_menus.sys.ini" server="77.222.40.220/2013/public_html/" local="130113936000000000" remote="130113936000000000" Dst="0" />
<file name="en-GB.com_messages.ini" server="77.222.40.220/2013/public_html/" local="130113936000000000" remote="130113936000000000" Dst="0" />
<file name="en-GB.com_messages.sys.ini" server="77.222.40.220/2013/public_html/" local="130113936000000000" remote="130113936000000000" Dst="0" />
<file name="en-GB.com_modules.ini" server="77.222.40.220/2013/public_html/" local="130113936000000000" remote="130113936000000000" Dst="0" />
<file name="en-GB.com_modules.sys.ini" server="77.222.40.220/2013/public_html/" local="130113936000000000" remote="130113936000000000" Dst="0" />
<file name="en-GB.com_newsfeeds.ini" server="77.222.40.220/2013/public_html/" local="130113936000000000" remote="130113936000000000" Dst="0" />
<file name="en-GB.com_newsfeeds.sys.ini" server="77.222.40.220/2013/public_html/" local="130113936000000000" remote="130113936000000000" Dst="0" />
<file name="en-GB.com_plugins.ini" server="77.222.40.220/2013/public_html/" local="130113936000000000" remote="130113936000000000" Dst="0" />
<file name="en-GB.com_plugins.sys.ini" server="77.222.40.220/2013/public_html/" local="130113936000000000" remote="130113936000000000" Dst="0" />
<file name="en-GB.com_redirect.ini" server="77.222.40.220/2013/public_html/" local="130113936000000000" remote="130113936000000000" Dst="0" />
<file name="en-GB.com_redirect.sys.ini" server="77.222.40.220/2013/public_html/" local="130113936000000000" remote="130113936000000000" Dst="0" />
<file name="en-GB.com_search.ini" server="77.222.40.220/2013/public_html/" local="130113936000000000" remote="130113936000000000" Dst="0" />
<file name="en-GB.com_search.sys.ini" server="77.222.40.220/2013/public_html/" local="130113936000000000" remote="130113936000000000" Dst="0" />
<file name="en-GB.com_templates.ini" server="77.222.40.220/2013/public_html/" local="130113936000000000" remote="130113936000000000" Dst="0" />
<file name="en-GB.com_templates.sys.ini" server="77.222.40.220/2013/public_html/" local="130113936000000000" remote="130113936000000000" Dst="0" />
<file name="en-GB.com_users.ini" server="77.222.40.220/2013/public_html/" local="130113936000000000" remote="130113936000000000" Dst="0" />
<file name="en-GB.com_users.sys.ini" server="77.222.40.220/2013/public_html/" local="130113936000000000" remote="130113936000000000" Dst="0" />
<file name="en-GB.com_virtuemart.ini" server="77.222.40.220/2013/public_html/" local="130041360000000000" remote="130041360000000000" Dst="0" />
<file name="en-GB.com_virtuemart.menu.ini" server="77.222.40.220/2013/public_html/" local="130041360000000000" remote="130041360000000000" Dst="0" />
<file name="en-GB.com_virtuemart.sys.ini" server="77.222.40.220/2013/public_html/" local="130041360000000000" remote="130041360000000000" Dst="0" />
<file name="en-GB.com_virtuemart_countries.ini" server="77.222.40.220/2013/public_html/" local="130041360000000000" remote="130041360000000000" Dst="0" />
<file name="en-GB.com_virtuemart_media.ini" server="77.222.40.220/2013/public_html/" local="130041360000000000" remote="130041360000000000" Dst="0" />
<file name="en-GB.com_weblinks.ini" server="77.222.40.220/2013/public_html/" local="130113936000000000" remote="130113936000000000" Dst="0" />
<file name="en-GB.com_weblinks.sys.ini" server="77.222.40.220/2013/public_html/" local="130113936000000000" remote="130113936000000000" Dst="0" />
<file name="en-GB.com_wrapper.ini" server="77.222.40.220/2013/public_html/" local="130113936000000000" remote="130113936000000000" Dst="0" />
<file name="en-GB.com_wrapper.sys.ini" server="77.222.40.220/2013/public_html/" local="130113936000000000" remote="130113936000000000" Dst="0" />
<file name="en-GB.ini" server="77.222.40.220/2013/public_html/" local="130113936000000000" remote="130113936000000000" Dst="0" />
<file name="en-GB.lib_joomla.ini" server="77.222.40.220/2013/public_html/" local="130113936000000000" remote="130113936000000000" Dst="0" />
<file name="en-GB.mod_custom.ini" server="77.222.40.220/2013/public_html/" local="130113936000000000" remote="130113936000000000" Dst="0" />
<file name="en-GB.mod_custom.sys.ini" server="77.222.40.220/2013/public_html/" local="130113936000000000" remote="130113936000000000" Dst="0" />
<file name="en-GB.mod_feed.ini" server="77.222.40.220/2013/public_html/" local="130113936000000000" remote="130113936000000000" Dst="0" />
<file name="en-GB.mod_feed.sys.ini" server="77.222.40.220/2013/public_html/" local="130113936000000000" remote="130113936000000000" Dst="0" />
<file name="en-GB.mod_latest.ini" server="77.222.40.220/2013/public_html/" local="130113936000000000" remote="130113936000000000" Dst="0" />
<file name="en-GB.mod_latest.sys.ini" server="77.222.40.220/2013/public_html/" local="130113936000000000" remote="130113936000000000" Dst="0" />
<file name="en-GB.mod_logged.ini" server="77.222.40.220/2013/public_html/" local="130113936000000000" remote="130113936000000000" Dst="0" />
<file name="en-GB.mod_logged.sys.ini" server="77.222.40.220/2013/public_html/" local="130113936000000000" remote="130113936000000000" Dst="0" />
<file name="en-GB.mod_login.ini" server="77.222.40.220/2013/public_html/" local="130113936000000000" remote="130113936000000000" Dst="0" />
<file name="en-GB.mod_login.sys.ini" server="77.222.40.220/2013/public_html/" local="130113936000000000" remote="130113936000000000" Dst="0" />
<file name="en-GB.mod_menu.ini" server="77.222.40.220/2013/public_html/" local="130113936000000000" remote="130113936000000000" Dst="0" />
<file name="en-GB.mod_menu.sys.ini" server="77.222.40.220/2013/public_html/" local="130113936000000000" remote="130113936000000000" Dst="0" />
<file name="en-GB.mod_multilangstatus.ini" server="77.222.40.220/2013/public_html/" local="130113936000000000" remote="130113936000000000" Dst="0" />
<file name="en-GB.mod_multilangstatus.sys.ini" server="77.222.40.220/2013/public_html/" local="130113936000000000" remote="130113936000000000" Dst="0" />
<file name="en-GB.mod_popular.ini" server="77.222.40.220/2013/public_html/" local="130113936000000000" remote="130113936000000000" Dst="0" />
<file name="en-GB.mod_popular.sys.ini" server="77.222.40.220/2013/public_html/" local="130113936000000000" remote="130113936000000000" Dst="0" />
<file name="en-GB.mod_quickicon.ini" server="77.222.40.220/2013/public_html/" local="130113936000000000" remote="130113936000000000" Dst="0" />
<file name="en-GB.mod_quickicon.sys.ini" server="77.222.40.220/2013/public_html/" local="130113936000000000" remote="130113936000000000" Dst="0" />
<file name="en-GB.mod_status.ini" server="77.222.40.220/2013/public_html/" local="130113936000000000" remote="130113936000000000" Dst="0" />
<file name="en-GB.mod_status.sys.ini" server="77.222.40.220/2013/public_html/" local="130113936000000000" remote="130113936000000000" Dst="0" />
<file name="en-GB.mod_submenu.ini" server="77.222.40.220/2013/public_html/" local="130113936000000000" remote="130113936000000000" Dst="0" />
<file name="en-GB.mod_submenu.sys.ini" server="77.222.40.220/2013/public_html/" local="130113936000000000" remote="130113936000000000" Dst="0" />
<file name="en-GB.mod_title.ini" server="77.222.40.220/2013/public_html/" local="130113936000000000" remote="130113936000000000" Dst="0" />
<file name="en-GB.mod_title.sys.ini" server="77.222.40.220/2013/public_html/" local="130113936000000000" remote="130113936000000000" Dst="0" />
<file name="en-GB.mod_toolbar.ini" server="77.222.40.220/2013/public_html/" local="130113936000000000" remote="130113936000000000" Dst="0" />
<file name="en-GB.mod_toolbar.sys.ini" server="77.222.40.220/2013/public_html/" local="130113936000000000" remote="130113936000000000" Dst="0" />
<file name="en-GB.mod_version.ini" server="77.222.40.220/2013/public_html/" local="130113936000000000" remote="130113936000000000" Dst="0" />
<file name="en-GB.mod_version.sys.ini" server="77.222.40.220/2013/public_html/" local="130113936000000000" remote="130113936000000000" Dst="0" />
<file name="en-GB.plg_authentication_gmail.ini" server="77.222.40.220/2013/public_html/" local="130113936000000000" remote="130113936000000000" Dst="0" />
<file name="en-GB.plg_authentication_gmail.sys.ini" server="77.222.40.220/2013/public_html/" local="130113936000000000" remote="130113936000000000" Dst="0" />
<file name="en-GB.plg_authentication_joomla.ini" server="77.222.40.220/2013/public_html/" local="130113936000000000" remote="130113936000000000" Dst="0" />
<file name="en-GB.plg_authentication_joomla.sys.ini" server="77.222.40.220/2013/public_html/" local="130113936000000000" remote="130113936000000000" Dst="0" />
<file name="en-GB.plg_authentication_ldap.ini" server="77.222.40.220/2013/public_html/" local="130113936000000000" remote="130113936000000000" Dst="0" />
<file name="en-GB.plg_authentication_ldap.sys.ini" server="77.222.40.220/2013/public_html/" local="130113936000000000" remote="130113936000000000" Dst="0" />
<file name="en-GB.plg_captcha_recaptcha.ini" server="77.222.40.220/2013/public_html/" local="130113936000000000" remote="130113936000000000" Dst="0" />
<file name="en-GB.plg_captcha_recaptcha.sys.ini" server="77.222.40.220/2013/public_html/" local="130113936000000000" remote="130113936000000000" Dst="0" />
<file name="en-GB.plg_content_emailcloak.ini" server="77.222.40.220/2013/public_html/" local="130113936000000000" remote="130113936000000000" Dst="0" />
<file name="en-GB.plg_content_emailcloak.sys.ini" server="77.222.40.220/2013/public_html/" local="130113936000000000" remote="130113936000000000" Dst="0" />
<file name="en-GB.plg_content_finder.ini" server="77.222.40.220/2013/public_html/" local="130113936000000000" remote="130113936000000000" Dst="0" />
<file name="en-GB.plg_content_finder.sys.ini" server="77.222.40.220/2013/public_html/" local="130113936000000000" remote="130113936000000000" Dst="0" />
<file name="en-GB.plg_content_geshi.ini" server="77.222.40.220/2013/public_html/" local="130113936000000000" remote="130113936000000000" Dst="0" />
<file name="en-GB.plg_content_geshi.sys.ini" server="77.222.40.220/2013/public_html/" local="130113936000000000" remote="130113936000000000" Dst="0" />
<file name="en-GB.plg_content_joomla.ini" server="77.222.40.220/2013/public_html/" local="130113936000000000" remote="130113936000000000" Dst="0" />
<file name="en-GB.plg_content_joomla.sys.ini" server="77.222.40.220/2013/public_html/" local="130113936000000000" remote="130113936000000000" Dst="0" />
<file name="en-GB.plg_content_loadmodule.ini" server="77.222.40.220/2013/public_html/" local="130113936000000000" remote="130113936000000000" Dst="0" />
<file name="en-GB.plg_content_loadmodule.sys.ini" server="77.222.40.220/2013/public_html/" local="130113936000000000" remote="130113936000000000" Dst="0" />
<file name="en-GB.plg_content_pagebreak.ini" server="77.222.40.220/2013/public_html/" local="130113936000000000" remote="130113936000000000" Dst="0" />
<file name="en-GB.plg_content_pagebreak.sys.ini" server="77.222.40.220/2013/public_html/" local="130113936000000000" remote="130113936000000000" Dst="0" />
<file name="en-GB.plg_content_pagenavigation.ini" server="77.222.40.220/2013/public_html/" local="130113936000000000" remote="130113936000000000" Dst="0" />
<file name="en-GB.plg_content_pagenavigation.sys.ini" server="77.222.40.220/2013/public_html/" local="130113936000000000" remote="130113936000000000" Dst="0" />
<file name="en-GB.plg_content_vote.ini" server="77.222.40.220/2013/public_html/" local="130113936000000000" remote="130113936000000000" Dst="0" />
<file name="en-GB.plg_content_vote.sys.ini" server="77.222.40.220/2013/public_html/" local="130113936000000000" remote="130113936000000000" Dst="0" />
<file name="en-GB.plg_editors-xtd_article.ini" server="77.222.40.220/2013/public_html/" local="130113936000000000" remote="130113936000000000" Dst="0" />
<file name="en-GB.plg_editors-xtd_article.sys.ini" server="77.222.40.220/2013/public_html/" local="130113936000000000" remote="130113936000000000" Dst="0" />
<file name="en-GB.plg_editors-xtd_image.ini" server="77.222.40.220/2013/public_html/" local="130113936000000000" remote="130113936000000000" Dst="0" />
<file name="en-GB.plg_editors-xtd_image.sys.ini" server="77.222.40.220/2013/public_html/" local="130113936000000000" remote="130113936000000000" Dst="0" />
<file name="en-GB.plg_editors-xtd_modulesanywhere.ini" server="77.222.40.220/2013/public_html/" local="130049136000000000" remote="130049136000000000" Dst="0" />
<file name="en-GB.plg_editors-xtd_modulesanywhere.sys.ini" server="77.222.40.220/2013/public_html/" local="130049136000000000" remote="130049136000000000" Dst="0" />
<file name="en-GB.plg_editors-xtd_pagebreak.ini" server="77.222.40.220/2013/public_html/" local="130113936000000000" remote="130113936000000000" Dst="0" />
<file name="en-GB.plg_editors-xtd_pagebreak.sys.ini" server="77.222.40.220/2013/public_html/" local="130113936000000000" remote="130113936000000000" Dst="0" />
<file name="en-GB.plg_editors-xtd_readmore.ini" server="77.222.40.220/2013/public_html/" local="130113936000000000" remote="130113936000000000" Dst="0" />
<file name="en-GB.plg_editors-xtd_readmore.sys.ini" server="77.222.40.220/2013/public_html/" local="130113936000000000" remote="130113936000000000" Dst="0" />
<file name="en-GB.plg_editors_codemirror.ini" server="77.222.40.220/2013/public_html/" local="130113936000000000" remote="130113936000000000" Dst="0" />
<file name="en-GB.plg_editors_codemirror.sys.ini" server="77.222.40.220/2013/public_html/" local="130113936000000000" remote="130113936000000000" Dst="0" />
<file name="en-GB.plg_editors_jce.ini" server="77.222.40.220/2013/public_html/" local="130043088000000000" remote="130043088000000000" Dst="0" />
<file name="en-GB.plg_editors_jce.sys.ini" server="77.222.40.220/2013/public_html/" local="130043088000000000" remote="130043088000000000" Dst="0" />
<file name="en-GB.plg_editors_none.ini" server="77.222.40.220/2013/public_html/" local="130113936000000000" remote="130113936000000000" Dst="0" />
<file name="en-GB.plg_editors_none.sys.ini" server="77.222.40.220/2013/public_html/" local="130113936000000000" remote="130113936000000000" Dst="0" />
<file name="en-GB.plg_editors_tinymce.ini" server="77.222.40.220/2013/public_html/" local="130113936000000000" remote="130113936000000000" Dst="0" />
<file name="en-GB.plg_editors_tinymce.sys.ini" server="77.222.40.220/2013/public_html/" local="130113936000000000" remote="130113936000000000" Dst="0" />
<file name="en-GB.plg_extension_joomla.ini" server="77.222.40.220/2013/public_html/" local="130113936000000000" remote="130113936000000000" Dst="0" />
<file name="en-GB.plg_extension_joomla.sys.ini" server="77.222.40.220/2013/public_html/" local="130113936000000000" remote="130113936000000000" Dst="0" />
<file name="en-GB.plg_finder_categories.ini" server="77.222.40.220/2013/public_html/" local="130113936000000000" remote="130113936000000000" Dst="0" />
<file name="en-GB.plg_finder_categories.sys.ini" server="77.222.40.220/2013/public_html/" local="130113936000000000" remote="130113936000000000" Dst="0" />
<file name="en-GB.plg_finder_contacts.ini" server="77.222.40.220/2013/public_html/" local="130113936000000000" remote="130113936000000000" Dst="0" />
<file name="en-GB.plg_finder_contacts.sys.ini" server="77.222.40.220/2013/public_html/" local="130113936000000000" remote="130113936000000000" Dst="0" />
<file name="en-GB.plg_finder_content.ini" server="77.222.40.220/2013/public_html/" local="130113936000000000" remote="130113936000000000" Dst="0" />
<file name="en-GB.plg_finder_content.sys.ini" server="77.222.40.220/2013/public_html/" local="130113936000000000" remote="130113936000000000" Dst="0" />
<file name="en-GB.plg_finder_newsfeeds.ini" server="77.222.40.220/2013/public_html/" local="130113936000000000" remote="130113936000000000" Dst="0" />
<file name="en-GB.plg_finder_newsfeeds.sys.ini" server="77.222.40.220/2013/public_html/" local="130113936000000000" remote="130113936000000000" Dst="0" />
<file name="en-GB.plg_finder_weblinks.ini" server="77.222.40.220/2013/public_html/" local="130113936000000000" remote="130113936000000000" Dst="0" />
<file name="en-GB.plg_finder_weblinks.sys.ini" server="77.222.40.220/2013/public_html/" local="130113936000000000" remote="130113936000000000" Dst="0" />
<file name="en-GB.plg_quickicon_extensionupdate.ini" server="77.222.40.220/2013/public_html/" local="130113936000000000" remote="130113936000000000" Dst="0" />
<file name="en-GB.plg_quickicon_extensionupdate.sys.ini" server="77.222.40.220/2013/public_html/" local="130113936000000000" remote="130113936000000000" Dst="0" />
<file name="en-GB.plg_quickicon_jcefilebrowser.ini" server="77.222.40.220/2013/public_html/" local="130043088000000000" remote="130043088000000000" Dst="0" />
<file name="en-GB.plg_quickicon_jcefilebrowser.sys.ini" server="77.222.40.220/2013/public_html/" local="130043088000000000" remote="130043088000000000" Dst="0" />
<file name="en-GB.plg_quickicon_joomlaupdate.ini" server="77.222.40.220/2013/public_html/" local="130113936000000000" remote="130113936000000000" Dst="0" />
<file name="en-GB.plg_quickicon_joomlaupdate.sys.ini" server="77.222.40.220/2013/public_html/" local="130113936000000000" remote="130113936000000000" Dst="0" />
<file name="en-GB.plg_search_categories.ini" server="77.222.40.220/2013/public_html/" local="130113936000000000" remote="130113936000000000" Dst="0" />
<file name="en-GB.plg_search_categories.sys.ini" server="77.222.40.220/2013/public_html/" local="130113936000000000" remote="130113936000000000" Dst="0" />
<file name="en-GB.plg_search_contacts.ini" server="77.222.40.220/2013/public_html/" local="130113936000000000" remote="130113936000000000" Dst="0" />
<file name="en-GB.plg_search_contacts.sys.ini" server="77.222.40.220/2013/public_html/" local="130113936000000000" remote="130113936000000000" Dst="0" />
<file name="en-GB.plg_search_content.ini" server="77.222.40.220/2013/public_html/" local="130113936000000000" remote="130113936000000000" Dst="0" />
<file name="en-GB.plg_search_content.sys.ini" server="77.222.40.220/2013/public_html/" local="130113936000000000" remote="130113936000000000" Dst="0" />
<file name="en-GB.plg_search_newsfeeds.ini" server="77.222.40.220/2013/public_html/" local="130113936000000000" remote="130113936000000000" Dst="0" />
<file name="en-GB.plg_search_newsfeeds.sys.ini" server="77.222.40.220/2013/public_html/" local="130113936000000000" remote="130113936000000000" Dst="0" />
<file name="en-GB.plg_search_weblinks.ini" server="77.222.40.220/2013/public_html/" local="130113936000000000" remote="130113936000000000" Dst="0" />
<file name="en-GB.plg_search_weblinks.sys.ini" server="77.222.40.220/2013/public_html/" local="130113936000000000" remote="130113936000000000" Dst="0" />
<file name="en-GB.plg_system_cache.ini" server="77.222.40.220/2013/public_html/" local="130113936000000000" remote="130113936000000000" Dst="0" />
<file name="en-GB.plg_system_cache.sys.ini" server="77.222.40.220/2013/public_html/" local="130113936000000000" remote="130113936000000000" Dst="0" />
<file name="en-GB.plg_system_debug.ini" server="77.222.40.220/2013/public_html/" local="130113936000000000" remote="130113936000000000" Dst="0" />
<file name="en-GB.plg_system_debug.sys.ini" server="77.222.40.220/2013/public_html/" local="130113936000000000" remote="130113936000000000" Dst="0" />
<file name="en-GB.plg_system_highlight.ini" server="77.222.40.220/2013/public_html/" local="130113936000000000" remote="130113936000000000" Dst="0" />
<file name="en-GB.plg_system_highlight.sys.ini" server="77.222.40.220/2013/public_html/" local="130113936000000000" remote="130113936000000000" Dst="0" />
<file name="en-GB.plg_system_languagecode.ini" server="77.222.40.220/2013/public_html/" local="130113936000000000" remote="130113936000000000" Dst="0" />
<file name="en-GB.plg_system_languagecode.sys.ini" server="77.222.40.220/2013/public_html/" local="130113936000000000" remote="130113936000000000" Dst="0" />
<file name="en-GB.plg_system_languagefilter.ini" server="77.222.40.220/2013/public_html/" local="130113936000000000" remote="130113936000000000" Dst="0" />
<file name="en-GB.plg_system_languagefilter.sys.ini" server="77.222.40.220/2013/public_html/" local="130113936000000000" remote="130113936000000000" Dst="0" />
<file name="en-GB.plg_system_log.ini" server="77.222.40.220/2013/public_html/" local="130113936000000000" remote="130113936000000000" Dst="0" />
<file name="en-GB.plg_system_log.sys.ini" server="77.222.40.220/2013/public_html/" local="130113936000000000" remote="130113936000000000" Dst="0" />
<file name="en-GB.plg_system_logout.ini" server="77.222.40.220/2013/public_html/" local="130113936000000000" remote="130113936000000000" Dst="0" />
<file name="en-GB.plg_system_logout.sys.ini" server="77.222.40.220/2013/public_html/" local="130113936000000000" remote="130113936000000000" Dst="0" />
<file name="en-GB.plg_system_modulesanywhere.ini" server="77.222.40.220/2013/public_html/" local="130049136000000000" remote="130049136000000000" Dst="0" />
<file name="en-GB.plg_system_modulesanywhere.sys.ini" server="77.222.40.220/2013/public_html/" local="130049136000000000" remote="130049136000000000" Dst="0" />
<file name="en-GB.plg_system_nnframework.ini" server="77.222.40.220/2013/public_html/" local="130049136000000000" remote="130049136000000000" Dst="0" />
<file name="en-GB.plg_system_nnframework.sys.ini" server="77.222.40.220/2013/public_html/" local="130049136000000000" remote="130049136000000000" Dst="0" />
<file name="en-GB.plg_system_p3p.ini" server="77.222.40.220/2013/public_html/" local="130113936000000000" remote="130113936000000000" Dst="0" />
<file name="en-GB.plg_system_p3p.sys.ini" server="77.222.40.220/2013/public_html/" local="130113936000000000" remote="130113936000000000" Dst="0" />
<file name="en-GB.plg_system_redirect.ini" server="77.222.40.220/2013/public_html/" local="130113936000000000" remote="130113936000000000" Dst="0" />
<file name="en-GB.plg_system_redirect.sys.ini" server="77.222.40.220/2013/public_html/" local="130113936000000000" remote="130113936000000000" Dst="0" />
<file name="en-GB.plg_system_remember.ini" server="77.222.40.220/2013/public_html/" local="130113936000000000" remote="130113936000000000" Dst="0" />
<file name="en-GB.plg_system_remember.sys.ini" server="77.222.40.220/2013/public_html/" local="130113936000000000" remote="130113936000000000" Dst="0" />
<file name="en-GB.plg_system_sef.ini" server="77.222.40.220/2013/public_html/" local="130113936000000000" remote="130113936000000000" Dst="0" />
<file name="en-GB.plg_system_sef.sys.ini" server="77.222.40.220/2013/public_html/" local="130113936000000000" remote="130113936000000000" Dst="0" />
<file name="en-GB.plg_user_contactcreator.ini" server="77.222.40.220/2013/public_html/" local="130113936000000000" remote="130113936000000000" Dst="0" />
<file name="en-GB.plg_user_contactcreator.sys.ini" server="77.222.40.220/2013/public_html/" local="130113936000000000" remote="130113936000000000" Dst="0" />
<file name="en-GB.plg_user_joomla.ini" server="77.222.40.220/2013/public_html/" local="130113936000000000" remote="130113936000000000" Dst="0" />
<file name="en-GB.plg_user_joomla.sys.ini" server="77.222.40.220/2013/public_html/" local="130113936000000000" remote="130113936000000000" Dst="0" />
<file name="en-GB.plg_user_profile.ini" server="77.222.40.220/2013/public_html/" local="130113936000000000" remote="130113936000000000" Dst="0" />
<file name="en-GB.plg_user_profile.sys.ini" server="77.222.40.220/2013/public_html/" local="130113936000000000" remote="130113936000000000" Dst="0" />
<file name="en-GB.plg_vmcalculation_avalara.ini" server="77.222.40.220/2013/public_html/" local="130041360000000000" remote="130041360000000000" Dst="0" />
<file name="en-GB.plg_vmcustom_specification.ini" server="77.222.40.220/2013/public_html/" local="130041360000000000" remote="130041360000000000" Dst="0" />
<file name="en-GB.plg_vmcustom_specification.sys.ini" server="77.222.40.220/2013/public_html/" local="130041360000000000" remote="130041360000000000" Dst="0" />
<file name="en-GB.plg_vmcustom_stockable.ini" server="77.222.40.220/2013/public_html/" local="130041360000000000" remote="130041360000000000" Dst="0" />
<file name="en-GB.plg_vmcustom_stockable.sys.ini" server="77.222.40.220/2013/public_html/" local="130041360000000000" remote="130041360000000000" Dst="0" />
<file name="en-GB.plg_vmcustom_textinput.ini" server="77.222.40.220/2013/public_html/" local="130041360000000000" remote="130041360000000000" Dst="0" />
<file name="en-GB.plg_vmcustom_textinput.sys.ini" server="77.222.40.220/2013/public_html/" local="130041360000000000" remote="130041360000000000" Dst="0" />
<file name="en-GB.plg_vmpayment_authorizenet.ini" server="77.222.40.220/2013/public_html/" local="130041360000000000" remote="130041360000000000" Dst="0" />
<file name="en-GB.plg_vmpayment_authorizenet.sys.ini" server="77.222.40.220/2013/public_html/" local="130041360000000000" remote="130041360000000000" Dst="0" />
<file name="en-GB.plg_vmpayment_heidelpay.ini" server="77.222.40.220/2013/public_html/" local="130041360000000000" remote="130041360000000000" Dst="0" />
<file name="en-GB.plg_vmpayment_heidelpay.sys.ini" server="77.222.40.220/2013/public_html/" local="130041360000000000" remote="130041360000000000" Dst="0" />
<file name="en-GB.plg_vmpayment_klarna.ini" server="77.222.40.220/2013/public_html/" local="130041360000000000" remote="130041360000000000" Dst="0" />
<file name="en-GB.plg_vmpayment_klarna.sys.ini" server="77.222.40.220/2013/public_html/" local="130041360000000000" remote="130041360000000000" Dst="0" />
<file name="en-GB.plg_vmpayment_moneybookers.ini" server="77.222.40.220/2013/public_html/" local="130041360000000000" remote="130041360000000000" Dst="0" />
<file name="en-GB.plg_vmpayment_moneybookers_acc.sys.ini" server="77.222.40.220/2013/public_html/" local="130041360000000000" remote="130041360000000000" Dst="0" />
<file name="en-GB.plg_vmpayment_moneybookers_did.sys.ini" server="77.222.40.220/2013/public_html/" local="130041360000000000" remote="130041360000000000" Dst="0" />
<file name="en-GB.plg_vmpayment_moneybookers_gir.sys.ini" server="77.222.40.220/2013/public_html/" local="130041360000000000" remote="130041360000000000" Dst="0" />
<file name="en-GB.plg_vmpayment_moneybookers_idl.sys.ini" server="77.222.40.220/2013/public_html/" local="130041360000000000" remote="130041360000000000" Dst="0" />
<file name="en-GB.plg_vmpayment_moneybookers_obt.sys.ini" server="77.222.40.220/2013/public_html/" local="130041360000000000" remote="130041360000000000" Dst="0" />
<file name="en-GB.plg_vmpayment_moneybookers_pwy.sys.ini" server="77.222.40.220/2013/public_html/" local="130041360000000000" remote="130041360000000000" Dst="0" />
<file name="en-GB.plg_vmpayment_moneybookers_sft.sys.ini" server="77.222.40.220/2013/public_html/" local="130041360000000000" remote="130041360000000000" Dst="0" />
<file name="en-GB.plg_vmpayment_moneybookers_wlt.sys.ini" server="77.222.40.220/2013/public_html/" local="130041360000000000" remote="130041360000000000" Dst="0" />
<file name="en-GB.plg_vmpayment_paypal.ini" server="77.222.40.220/2013/public_html/" local="130041360000000000" remote="130041360000000000" Dst="0" />
<file name="en-GB.plg_vmpayment_paypal.sys.ini" server="77.222.40.220/2013/public_html/" local="130041360000000000" remote="130041360000000000" Dst="0" />
<file name="en-GB.plg_vmpayment_payzen.ini" server="77.222.40.220/2013/public_html/" local="130041360000000000" remote="130041360000000000" Dst="0" />
<file name="en-GB.plg_vmpayment_payzen.sys.ini" server="77.222.40.220/2013/public_html/" local="130041360000000000" remote="130041360000000000" Dst="0" />
<file name="en-GB.plg_vmpayment_standard.ini" server="77.222.40.220/2013/public_html/" local="130041360000000000" remote="130041360000000000" Dst="0" />
<file name="en-GB.plg_vmpayment_standard.sys.ini" server="77.222.40.220/2013/public_html/" local="130041360000000000" remote="130041360000000000" Dst="0" />
<file name="en-GB.plg_vmpayment_systempay.ini" server="77.222.40.220/2013/public_html/" local="130041360000000000" remote="130041360000000000" Dst="0" />
<file name="en-GB.plg_vmpayment_systempay.sys.ini" server="77.222.40.220/2013/public_html/" local="130041360000000000" remote="130041360000000000" Dst="0" />
<file name="en-GB.plg_vmshipment_weight_countries.ini" server="77.222.40.220/2013/public_html/" local="130041360000000000" remote="130041360000000000" Dst="0" />
<file name="en-GB.plg_vmshipment_weight_countries.sys.ini" server="77.222.40.220/2013/public_html/" local="130041360000000000" remote="130041360000000000" Dst="0" />
<file name="en-GB.tpl_bluestork.ini" server="77.222.40.220/2013/public_html/" local="130113936000000000" remote="130113936000000000" Dst="0" />
<file name="en-GB.tpl_bluestork.sys.ini" server="77.222.40.220/2013/public_html/" local="130113936000000000" remote="130113936000000000" Dst="0" />
<file name="en-GB.tpl_hathor.ini" server="77.222.40.220/2013/public_html/" local="130113936000000000" remote="130113936000000000" Dst="0" />
<file name="en-GB.tpl_hathor.sys.ini" server="77.222.40.220/2013/public_html/" local="130113936000000000" remote="130113936000000000" Dst="0" />
<file name="en-GB.com_admin.ini" server="I:/auction-ruseasons/" local="130476590828466000" remote="130476590840000000" Dst="0" />
<file name="en-GB.com_admin.sys.ini" server="I:/auction-ruseasons/" local="130476590828476000" remote="130476590840000000" Dst="0" />
<file name="en-GB.com_banners.ini" server="I:/auction-ruseasons/" local="130476590828486000" remote="130476590840000000" Dst="0" />
<file name="en-GB.com_banners.sys.ini" server="I:/auction-ruseasons/" local="130476590828496000" remote="130476590840000000" Dst="0" />
<file name="en-GB.com_cache.ini" server="I:/auction-ruseasons/" local="130476590828656000" remote="130476590840000000" Dst="0" />
<file name="en-GB.com_cache.sys.ini" server="I:/auction-ruseasons/" local="130476590828666000" remote="130476590840000000" Dst="0" />
<file name="en-GB.com_categories.ini" server="I:/auction-ruseasons/" local="130476590828676000" remote="130476590840000000" Dst="0" />
<file name="en-GB.com_categories.sys.ini" server="I:/auction-ruseasons/" local="130476590828686000" remote="130476590840000000" Dst="0" />
<file name="en-GB.com_checkin.ini" server="I:/auction-ruseasons/" local="130476590828696000" remote="130476590840000000" Dst="0" />
<file name="en-GB.com_checkin.sys.ini" server="I:/auction-ruseasons/" local="130476590828706000" remote="130476590840000000" Dst="0" />
<file name="en-GB.com_config.ini" server="I:/auction-ruseasons/" local="130476590828716000" remote="130476590840000000" Dst="0" />
<file name="en-GB.com_config.sys.ini" server="I:/auction-ruseasons/" local="130476590828726000" remote="130476590840000000" Dst="0" />
<file name="en-GB.com_contact.ini" server="I:/auction-ruseasons/" local="130476590828736000" remote="130476590840000000" Dst="0" />
<file name="en-GB.com_contact.sys.ini" server="I:/auction-ruseasons/" local="130476590828756000" remote="130476590840000000" Dst="0" />
<file name="en-GB.com_content.ini" server="I:/auction-ruseasons/" local="130476590828766000" remote="130476590840000000" Dst="0" />
<file name="en-GB.com_content.sys.ini" server="I:/auction-ruseasons/" local="130476590828776000" remote="130476590840000000" Dst="0" />
<file name="en-GB.com_cpanel.ini" server="I:/auction-ruseasons/" local="130476590828786000" remote="130476590840000000" Dst="0" />
<file name="en-GB.com_cpanel.sys.ini" server="I:/auction-ruseasons/" local="130476590828796000" remote="130476590840000000" Dst="0" />
<file name="en-GB.com_finder.ini" server="I:/auction-ruseasons/" local="130476590828806000" remote="130476590840000000" Dst="0" />
<file name="en-GB.com_finder.sys.ini" server="I:/auction-ruseasons/" local="130476590828816000" remote="130476590840000000" Dst="0" />
<file name="en-GB.com_installer.ini" server="I:/auction-ruseasons/" local="130476590828846000" remote="130476590840000000" Dst="0" />
<file name="en-GB.com_installer.sys.ini" server="I:/auction-ruseasons/" local="130476590828866000" remote="130476590840000000" Dst="0" />
<file name="en-GB.com_jce.ini" server="I:/auction-ruseasons/" local="130476590828886000" remote="130476590840000000" Dst="0" />
<file name="en-GB.com_jce.sys.ini" server="I:/auction-ruseasons/" local="130476590828906000" remote="130476590840000000" Dst="0" />
<file name="en-GB.com_joomlaupdate.ini" server="I:/auction-ruseasons/" local="130476590828916000" remote="130476590840000000" Dst="0" />
<file name="en-GB.com_joomlaupdate.sys.ini" server="I:/auction-ruseasons/" local="130476590828926000" remote="130476590840000000" Dst="0" />
<file name="en-GB.com_languages.ini" server="I:/auction-ruseasons/" local="130476590828936000" remote="130476590840000000" Dst="0" />
<file name="en-GB.com_languages.sys.ini" server="I:/auction-ruseasons/" local="130476590828946000" remote="130476590840000000" Dst="0" />
<file name="en-GB.com_login.ini" server="I:/auction-ruseasons/" local="130476590828956000" remote="130476590840000000" Dst="0" />
<file name="en-GB.com_login.sys.ini" server="I:/auction-ruseasons/" local="130476590829026000" remote="130476590840000000" Dst="0" />
<file name="en-GB.com_mailto.sys.ini" server="I:/auction-ruseasons/" local="130476590829036000" remote="130476590840000000" Dst="0" />
<file name="en-GB.com_media.ini" server="I:/auction-ruseasons/" local="130476590829046000" remote="130476590840000000" Dst="0" />
<file name="en-GB.com_media.sys.ini" server="I:/auction-ruseasons/" local="130476590829056000" remote="130476590840000000" Dst="0" />
<file name="en-GB.com_menus.ini" server="I:/auction-ruseasons/" local="130476590829066000" remote="130476590840000000" Dst="0" />
<file name="en-GB.com_menus.sys.ini" server="I:/auction-ruseasons/" local="130476590829086000" remote="130476590840000000" Dst="0" />
<file name="en-GB.com_messages.ini" server="I:/auction-ruseasons/" local="130476590829096000" remote="130476590840000000" Dst="0" />
<file name="en-GB.com_messages.sys.ini" server="I:/auction-ruseasons/" local="130476590829106000" remote="130476590840000000" Dst="0" />
<file name="en-GB.com_modules.ini" server="I:/auction-ruseasons/" local="130476590829116000" remote="130476590840000000" Dst="0" />
<file name="en-GB.com_modules.sys.ini" server="I:/auction-ruseasons/" local="130476590829136000" remote="130476590840000000" Dst="0" />
<file name="en-GB.com_newsfeeds.ini" server="I:/auction-ruseasons/" local="130476590829146000" remote="130476590840000000" Dst="0" />
<file name="en-GB.com_newsfeeds.sys.ini" server="I:/auction-ruseasons/" local="130476590829156000" remote="130476590840000000" Dst="0" />
<file name="en-GB.com_plugins.ini" server="I:/auction-ruseasons/" local="130476590829166000" remote="130476590840000000" Dst="0" />
<file name="en-GB.com_plugins.sys.ini" server="I:/auction-ruseasons/" local="130476590829186000" remote="130476590840000000" Dst="0" />
<file name="en-GB.com_redirect.ini" server="I:/auction-ruseasons/" local="130476590829196000" remote="130476590840000000" Dst="0" />
<file name="en-GB.com_redirect.sys.ini" server="I:/auction-ruseasons/" local="130476590829206000" remote="130476590840000000" Dst="0" />
<file name="en-GB.com_search.ini" server="I:/auction-ruseasons/" local="130476590829226000" remote="130476590840000000" Dst="0" />
<file name="en-GB.com_search.sys.ini" server="I:/auction-ruseasons/" local="130476590829246000" remote="130476590840000000" Dst="0" />
<file name="en-GB.com_templates.ini" server="I:/auction-ruseasons/" local="130476590829256000" remote="130476590840000000" Dst="0" />
<file name="en-GB.com_templates.sys.ini" server="I:/auction-ruseasons/" local="130476590829266000" remote="130476590840000000" Dst="0" />
<file name="en-GB.com_users.ini" server="I:/auction-ruseasons/" local="130476590829276000" remote="130476590840000000" Dst="0" />
<file name="en-GB.com_users.sys.ini" server="I:/auction-ruseasons/" local="130476590829286000" remote="130476590840000000" Dst="0" />
<file name="en-GB.com_virtuemart.ini" server="I:/auction-ruseasons/" local="130476590829316000" remote="130476590840000000" Dst="0" />
<file name="en-GB.com_virtuemart_countries.ini" server="I:/auction-ruseasons/" local="130476590829326000" remote="130476590840000000" Dst="0" />
<file name="en-GB.com_virtuemart_media.ini" server="I:/auction-ruseasons/" local="130476590829346000" remote="130476590840000000" Dst="0" />
<file name="en-GB.com_weblinks.ini" server="I:/auction-ruseasons/" local="130476590829356000" remote="130476590840000000" Dst="0" />
<file name="en-GB.com_weblinks.sys.ini" server="I:/auction-ruseasons/" local="130476590829356000" remote="130476590840000000" Dst="0" />
<file name="en-GB.com_wrapper.ini" server="I:/auction-ruseasons/" local="130476590829376000" remote="130476590840000000" Dst="0" />
<file name="en-GB.com_wrapper.sys.ini" server="I:/auction-ruseasons/" local="130476590829396000" remote="130476590840000000" Dst="0" />
<file name="en-GB.ini" server="I:/auction-ruseasons/" local="130476590829416000" remote="130476590840000000" Dst="0" />
<file name="en-GB.lib_joomla.ini" server="I:/auction-ruseasons/" local="130476590829436000" remote="130476590840000000" Dst="0" />
<file name="en-GB.localise.php" server="I:/auction-ruseasons/" local="130419717477250000" remote="130419717480000000" Dst="0" />
<file name="en-GB.mod_custom.ini" server="I:/auction-ruseasons/" local="130476590829446000" remote="130476590840000000" Dst="0" />
<file name="en-GB.mod_custom.sys.ini" server="I:/auction-ruseasons/" local="130476590829456000" remote="130476590840000000" Dst="0" />
<file name="en-GB.mod_feed.ini" server="I:/auction-ruseasons/" local="130476590829466000" remote="130476590840000000" Dst="0" />
<file name="en-GB.mod_feed.sys.ini" server="I:/auction-ruseasons/" local="130476590829476000" remote="130476590840000000" Dst="0" />
<file name="en-GB.mod_latest.ini" server="I:/auction-ruseasons/" local="130476590829486000" remote="130476590840000000" Dst="0" />
<file name="en-GB.mod_latest.sys.ini" server="I:/auction-ruseasons/" local="130476590829496000" remote="130476590840000000" Dst="0" />
<file name="en-GB.mod_logged.ini" server="I:/auction-ruseasons/" local="130476590829516000" remote="130476590840000000" Dst="0" />
<file name="en-GB.mod_logged.sys.ini" server="I:/auction-ruseasons/" local="130476590829526000" remote="130476590840000000" Dst="0" />
<file name="en-GB.mod_login.ini" server="I:/auction-ruseasons/" local="130476590829546000" remote="130476590840000000" Dst="0" />
<file name="en-GB.mod_login.sys.ini" server="I:/auction-ruseasons/" local="130476590829556000" remote="130476590840000000" Dst="0" />
<file name="en-GB.mod_menu.ini" server="I:/auction-ruseasons/" local="130476590829566000" remote="130476590840000000" Dst="0" />
<file name="en-GB.mod_menu.sys.ini" server="I:/auction-ruseasons/" local="130476590829576000" remote="130476590840000000" Dst="0" />
<file name="en-GB.mod_multilangstatus.ini" server="I:/auction-ruseasons/" local="130476590829586000" remote="130476590840000000" Dst="0" />
<file name="en-GB.mod_multilangstatus.sys.ini" server="I:/auction-ruseasons/" local="130476590829606000" remote="130476590840000000" Dst="0" />
<file name="en-GB.mod_popular.ini" server="I:/auction-ruseasons/" local="130476590829616000" remote="130476590840000000" Dst="0" />
<file name="en-GB.mod_popular.sys.ini" server="I:/auction-ruseasons/" local="130476590829626000" remote="130476590840000000" Dst="0" />
<file name="en-GB.mod_quickicon.ini" server="I:/auction-ruseasons/" local="130476590829636000" remote="130476590840000000" Dst="0" />
<file name="en-GB.mod_quickicon.sys.ini" server="I:/auction-ruseasons/" local="130476590829646000" remote="130476590840000000" Dst="0" />
<file name="en-GB.mod_status.ini" server="I:/auction-ruseasons/" local="130476590829656000" remote="130476590840000000" Dst="0" />
<file name="en-GB.mod_status.sys.ini" server="I:/auction-ruseasons/" local="130476590829686000" remote="130476590840000000" Dst="0" />
<file name="en-GB.mod_submenu.ini" server="I:/auction-ruseasons/" local="130476590829696000" remote="130476590840000000" Dst="0" />
<file name="en-GB.mod_submenu.sys.ini" server="I:/auction-ruseasons/" local="130476590829706000" remote="130476590840000000" Dst="0" />
<file name="en-GB.mod_title.ini" server="I:/auction-ruseasons/" local="130476590829716000" remote="130476590840000000" Dst="0" />
<file name="en-GB.mod_title.sys.ini" server="I:/auction-ruseasons/" local="130476590829726000" remote="130476590840000000" Dst="0" />
<file name="en-GB.mod_toolbar.ini" server="I:/auction-ruseasons/" local="130476590829746000" remote="130476590840000000" Dst="0" />
<file name="en-GB.mod_toolbar.sys.ini" server="I:/auction-ruseasons/" local="130476590829756000" remote="130476590840000000" Dst="0" />
<file name="en-GB.mod_version.ini" server="I:/auction-ruseasons/" local="130476590829766000" remote="130476590840000000" Dst="0" />
<file name="en-GB.mod_version.sys.ini" server="I:/auction-ruseasons/" local="130476590829776000" remote="130476590840000000" Dst="0" />
<file name="en-GB.plg_authentication_gmail.ini" server="I:/auction-ruseasons/" local="130476590829796000" remote="130476590840000000" Dst="0" />
<file name="en-GB.plg_authentication_gmail.sys.ini" server="I:/auction-ruseasons/" local="130476590829806000" remote="130476590840000000" Dst="0" />
<file name="en-GB.plg_authentication_joomla.ini" server="I:/auction-ruseasons/" local="130476590829816000" remote="130476590840000000" Dst="0" />
<file name="en-GB.plg_authentication_joomla.sys.ini" server="I:/auction-ruseasons/" local="130476590829826000" remote="130476590840000000" Dst="0" />
<file name="en-GB.plg_authentication_ldap.ini" server="I:/auction-ruseasons/" local="130476590829846000" remote="130476590840000000" Dst="0" />
<file name="en-GB.plg_authentication_ldap.sys.ini" server="I:/auction-ruseasons/" local="130476590829856000" remote="130476590840000000" Dst="0" />
<file name="en-GB.plg_captcha_recaptcha.ini" server="I:/auction-ruseasons/" local="130476590829866000" remote="130476590840000000" Dst="0" />
<file name="en-GB.plg_captcha_recaptcha.sys.ini" server="I:/auction-ruseasons/" local="130476590829876000" remote="130476590840000000" Dst="0" />
<file name="en-GB.plg_content_emailcloak.ini" server="I:/auction-ruseasons/" local="130476590829886000" remote="130476590840000000" Dst="0" />
<file name="en-GB.plg_content_emailcloak.sys.ini" server="I:/auction-ruseasons/" local="130476590829906000" remote="130476590840000000" Dst="0" />
<file name="en-GB.plg_content_finder.ini" server="I:/auction-ruseasons/" local="130476590829916000" remote="130476590840000000" Dst="0" />
<file name="en-GB.plg_content_finder.sys.ini" server="I:/auction-ruseasons/" local="130476590829926000" remote="130476590840000000" Dst="0" />
<file name="en-GB.plg_content_geshi.ini" server="I:/auction-ruseasons/" local="130476590829936000" remote="130476590840000000" Dst="0" />
<file name="en-GB.plg_content_geshi.sys.ini" server="I:/auction-ruseasons/" local="130476590829946000" remote="130476590840000000" Dst="0" />
<file name="en-GB.plg_content_joomla.ini" server="I:/auction-ruseasons/" local="130476590829956000" remote="130476590840000000" Dst="0" />
<file name="en-GB.plg_content_joomla.sys.ini" server="I:/auction-ruseasons/" local="130476590829966000" remote="130476590840000000" Dst="0" />
<file name="en-GB.plg_content_loadmodule.ini" server="I:/auction-ruseasons/" local="130476590829976000" remote="130476590840000000" Dst="0" />
<file name="en-GB.plg_content_loadmodule.sys.ini" server="I:/auction-ruseasons/" local="130476590830016000" remote="130476590840000000" Dst="0" />
<file name="en-GB.plg_content_pagebreak.ini" server="I:/auction-ruseasons/" local="130476590830026000" remote="130476590840000000" Dst="0" />
<file name="en-GB.plg_content_pagebreak.sys.ini" server="I:/auction-ruseasons/" local="130476590830036000" remote="130476590840000000" Dst="0" />
<file name="en-GB.plg_content_pagenavigation.ini" server="I:/auction-ruseasons/" local="130476590830056000" remote="130476590840000000" Dst="0" />
<file name="en-GB.plg_content_pagenavigation.sys.ini" server="I:/auction-ruseasons/" local="130476590830066000" remote="130476590840000000" Dst="0" />
<file name="en-GB.plg_content_vote.ini" server="I:/auction-ruseasons/" local="130476590830076000" remote="130476590840000000" Dst="0" />
<file name="en-GB.plg_content_vote.sys.ini" server="I:/auction-ruseasons/" local="130476590830086000" remote="130476590840000000" Dst="0" />
<file name="en-GB.plg_editors-xtd_article.ini" server="I:/auction-ruseasons/" local="130476590830096000" remote="130476590840000000" Dst="0" />
<file name="en-GB.plg_editors-xtd_article.sys.ini" server="I:/auction-ruseasons/" local="130476590830106000" remote="130476590840000000" Dst="0" />
<file name="en-GB.plg_editors-xtd_image.ini" server="I:/auction-ruseasons/" local="130476590830116000" remote="130476590840000000" Dst="0" />
<file name="en-GB.plg_editors-xtd_image.sys.ini" server="I:/auction-ruseasons/" local="130476590830126000" remote="130476590840000000" Dst="0" />
<file name="en-GB.plg_editors-xtd_pagebreak.ini" server="I:/auction-ruseasons/" local="130476590830136000" remote="130476590840000000" Dst="0" />
<file name="en-GB.plg_editors-xtd_pagebreak.sys.ini" server="I:/auction-ruseasons/" local="130476590830156000" remote="130476590840000000" Dst="0" />
<file name="en-GB.plg_editors-xtd_readmore.ini" server="I:/auction-ruseasons/" local="130476590830176000" remote="130476590840000000" Dst="0" />
<file name="en-GB.plg_editors-xtd_readmore.sys.ini" server="I:/auction-ruseasons/" local="130476590830196000" remote="130476590840000000" Dst="0" />
<file name="en-GB.plg_editors_codemirror.ini" server="I:/auction-ruseasons/" local="130476590830196000" remote="130476590840000000" Dst="0" />
<file name="en-GB.plg_editors_codemirror.sys.ini" server="I:/auction-ruseasons/" local="130476590830216000" remote="130476590840000000" Dst="0" />
<file name="en-GB.plg_editors_jce.ini" server="I:/auction-ruseasons/" local="130476590830226000" remote="130476590840000000" Dst="0" />
<file name="en-GB.plg_editors_jce.sys.ini" server="I:/auction-ruseasons/" local="130476590830236000" remote="130476590840000000" Dst="0" />
<file name="en-GB.plg_editors_none.ini" server="I:/auction-ruseasons/" local="130476590830246000" remote="130476590840000000" Dst="0" />
<file name="en-GB.plg_editors_none.sys.ini" server="I:/auction-ruseasons/" local="130476590830256000" remote="130476590840000000" Dst="0" />
<file name="en-GB.plg_editors_tinymce.ini" server="I:/auction-ruseasons/" local="130476590830276000" remote="130476590840000000" Dst="0" />
<file name="en-GB.plg_editors_tinymce.sys.ini" server="I:/auction-ruseasons/" local="130476590830286000" remote="130476590840000000" Dst="0" />
<file name="en-GB.plg_extension_joomla.ini" server="I:/auction-ruseasons/" local="130476590830296000" remote="130476590840000000" Dst="0" />
<file name="en-GB.plg_extension_joomla.sys.ini" server="I:/auction-ruseasons/" local="130476590830296000" remote="130476590840000000" Dst="0" />
<file name="en-GB.plg_finder_categories.ini" server="I:/auction-ruseasons/" local="130476590830316000" remote="130476590840000000" Dst="0" />
<file name="en-GB.plg_finder_categories.sys.ini" server="I:/auction-ruseasons/" local="130476590830326000" remote="130476590840000000" Dst="0" />
<file name="en-GB.plg_finder_contacts.ini" server="I:/auction-ruseasons/" local="130476590830356000" remote="130476590840000000" Dst="0" />
<file name="en-GB.plg_finder_contacts.sys.ini" server="I:/auction-ruseasons/" local="130476590830366000" remote="130476590840000000" Dst="0" />
<file name="en-GB.plg_finder_content.ini" server="I:/auction-ruseasons/" local="130476590830376000" remote="130476590840000000" Dst="0" />
<file name="en-GB.plg_finder_content.sys.ini" server="I:/auction-ruseasons/" local="130476590830396000" remote="130476590840000000" Dst="0" />
<file name="en-GB.plg_finder_newsfeeds.ini" server="I:/auction-ruseasons/" local="130476590830406000" remote="130476590840000000" Dst="0" />
<file name="en-GB.plg_finder_newsfeeds.sys.ini" server="I:/auction-ruseasons/" local="130476590830416000" remote="130476590840000000" Dst="0" />
<file name="en-GB.plg_finder_weblinks.ini" server="I:/auction-ruseasons/" local="130476590830426000" remote="130476590840000000" Dst="0" />
<file name="en-GB.plg_finder_weblinks.sys.ini" server="I:/auction-ruseasons/" local="130476590830436000" remote="130476590840000000" Dst="0" />
<file name="en-GB.plg_quickicon_extensionupdate.ini" server="I:/auction-ruseasons/" local="130476590830446000" remote="130476590840000000" Dst="0" />
<file name="en-GB.plg_quickicon_extensionupdate.sys.ini" server="I:/auction-ruseasons/" local="130476590830466000" remote="130476590840000000" Dst="0" />
<file name="en-GB.plg_quickicon_joomlaupdate.ini" server="I:/auction-ruseasons/" local="130476590830476000" remote="130476590840000000" Dst="0" />
<file name="en-GB.plg_quickicon_joomlaupdate.sys.ini" server="I:/auction-ruseasons/" local="130476590830486000" remote="130476590840000000" Dst="0" />
<file name="en-GB.plg_search_categories.ini" server="I:/auction-ruseasons/" local="130476590830496000" remote="130476590840000000" Dst="0" />
<file name="en-GB.plg_search_categories.sys.ini" server="I:/auction-ruseasons/" local="130476590830526000" remote="130476590840000000" Dst="0" />
<file name="en-GB.plg_search_contacts.ini" server="I:/auction-ruseasons/" local="130476590830536000" remote="130476590840000000" Dst="0" />
<file name="en-GB.plg_search_contacts.sys.ini" server="I:/auction-ruseasons/" local="130476590830546000" remote="130476590840000000" Dst="0" />
<file name="en-GB.plg_search_content.ini" server="I:/auction-ruseasons/" local="130476590830556000" remote="130476590840000000" Dst="0" />
<file name="en-GB.plg_search_content.sys.ini" server="I:/auction-ruseasons/" local="130476590830576000" remote="130476590840000000" Dst="0" />
<file name="en-GB.plg_search_newsfeeds.ini" server="I:/auction-ruseasons/" local="130476590830586000" remote="130476590840000000" Dst="0" />
<file name="en-GB.plg_search_newsfeeds.sys.ini" server="I:/auction-ruseasons/" local="130476590830596000" remote="130476590840000000" Dst="0" />
<file name="en-GB.plg_search_weblinks.ini" server="I:/auction-ruseasons/" local="130476590830606000" remote="130476590840000000" Dst="0" />
<file name="en-GB.plg_search_weblinks.sys.ini" server="I:/auction-ruseasons/" local="130476590830616000" remote="130476590840000000" Dst="0" />
<file name="en-GB.plg_system_cache.ini" server="I:/auction-ruseasons/" local="130476590830636000" remote="130476590840000000" Dst="0" />
<file name="en-GB.plg_system_cache.sys.ini" server="I:/auction-ruseasons/" local="130476590830646000" remote="130476590840000000" Dst="0" />
<file name="en-GB.plg_system_debug.ini" server="I:/auction-ruseasons/" local="130476590830656000" remote="130476590840000000" Dst="0" />
<file name="en-GB.plg_system_debug.sys.ini" server="I:/auction-ruseasons/" local="130476590830686000" remote="130476590840000000" Dst="0" />
<file name="en-GB.plg_system_highlight.ini" server="I:/auction-ruseasons/" local="130476590830696000" remote="130476590840000000" Dst="0" />
<file name="en-GB.plg_system_highlight.sys.ini" server="I:/auction-ruseasons/" local="130476590830706000" remote="130476590840000000" Dst="0" />
<file name="en-GB.plg_system_languagecode.ini" server="I:/auction-ruseasons/" local="130476590830716000" remote="130476590840000000" Dst="0" />
<file name="en-GB.plg_system_languagecode.sys.ini" server="I:/auction-ruseasons/" local="130476590830726000" remote="130476590840000000" Dst="0" />
<file name="en-GB.plg_system_languagefilter.ini" server="I:/auction-ruseasons/" local="130476590830746000" remote="130476590840000000" Dst="0" />
<file name="en-GB.plg_system_languagefilter.sys.ini" server="I:/auction-ruseasons/" local="130476590830756000" remote="130476590840000000" Dst="0" />
<file name="en-GB.plg_system_log.ini" server="I:/auction-ruseasons/" local="130476590830766000" remote="130476590840000000" Dst="0" />
<file name="en-GB.plg_system_log.sys.ini" server="I:/auction-ruseasons/" local="130476590830776000" remote="130476590840000000" Dst="0" />
<file name="en-GB.plg_system_logout.ini" server="I:/auction-ruseasons/" local="130476590830786000" remote="130476590840000000" Dst="0" />
<file name="en-GB.plg_system_logout.sys.ini" server="I:/auction-ruseasons/" local="130476590830806000" remote="130476590840000000" Dst="0" />
<file name="en-GB.plg_system_p3p.ini" server="I:/auction-ruseasons/" local="130476590830816000" remote="130476590840000000" Dst="0" />
<file name="en-GB.plg_system_p3p.sys.ini" server="I:/auction-ruseasons/" local="130476590830826000" remote="130476590840000000" Dst="0" />
<file name="en-GB.plg_system_redirect.ini" server="I:/auction-ruseasons/" local="130476590830836000" remote="130476590840000000" Dst="0" />
<file name="en-GB.plg_system_redirect.sys.ini" server="I:/auction-ruseasons/" local="130476590830856000" remote="130476590840000000" Dst="0" />
<file name="en-GB.plg_system_remember.ini" server="I:/auction-ruseasons/" local="130476590830866000" remote="130476590840000000" Dst="0" />
<file name="en-GB.plg_system_remember.sys.ini" server="I:/auction-ruseasons/" local="130476590830876000" remote="130476590840000000" Dst="0" />
<file name="en-GB.plg_system_sef.ini" server="I:/auction-ruseasons/" local="130476590830886000" remote="130476590840000000" Dst="0" />
<file name="en-GB.plg_system_sef.sys.ini" server="I:/auction-ruseasons/" local="130476590830896000" remote="130476590840000000" Dst="0" />
<file name="en-GB.plg_user_contactcreator.ini" server="I:/auction-ruseasons/" local="130476590830906000" remote="130476590840000000" Dst="0" />
<file name="en-GB.plg_user_contactcreator.sys.ini" server="I:/auction-ruseasons/" local="130476590830916000" remote="130476590840000000" Dst="0" />
<file name="en-GB.plg_user_joomla.ini" server="I:/auction-ruseasons/" local="130476590830936000" remote="130476590840000000" Dst="0" />
<file name="en-GB.plg_user_joomla.sys.ini" server="I:/auction-ruseasons/" local="130476590830946000" remote="130476590840000000" Dst="0" />
<file name="en-GB.plg_user_profile.ini" server="I:/auction-ruseasons/" local="130476590830956000" remote="130476590840000000" Dst="0" />
<file name="en-GB.plg_user_profile.sys.ini" server="I:/auction-ruseasons/" local="130476590830966000" remote="130476590840000000" Dst="0" />
<file name="en-GB.plg_vmcalculation_avalara.ini" server="I:/auction-ruseasons/" local="130476590830976000" remote="130476590840000000" Dst="0" />
<file name="en-GB.plg_vmcustom_specification.ini" server="I:/auction-ruseasons/" local="130476590830986000" remote="130476590840000000" Dst="0" />
<file name="en-GB.plg_vmcustom_specification.sys.ini" server="I:/auction-ruseasons/" local="130476590830996000" remote="130476590840000000" Dst="0" />
<file name="en-GB.plg_vmcustom_stockable.ini" server="I:/auction-ruseasons/" local="130476590831026000" remote="130476590840000000" Dst="0" />
<file name="en-GB.plg_vmcustom_stockable.sys.ini" server="I:/auction-ruseasons/" local="130476590831036000" remote="130476590840000000" Dst="0" />
<file name="en-GB.plg_vmcustom_textinput.ini" server="I:/auction-ruseasons/" local="130476590831046000" remote="130476590840000000" Dst="0" />
<file name="en-GB.plg_vmcustom_textinput.sys.ini" server="I:/auction-ruseasons/" local="130476590831056000" remote="130476590840000000" Dst="0" />
<file name="en-GB.plg_vmpayment_heidelpay.ini" server="I:/auction-ruseasons/" local="130476590831066000" remote="130476590840000000" Dst="0" />
<file name="en-GB.plg_vmpayment_payzen.ini" server="I:/auction-ruseasons/" local="130476590831086000" remote="130476590840000000" Dst="0" />
<file name="en-GB.plg_vmpayment_systempay.ini" server="I:/auction-ruseasons/" local="130476590831106000" remote="130476590840000000" Dst="0" />
<file name="en-GB.tpl_bluestork.ini" server="I:/auction-ruseasons/" local="130476590831116000" remote="130476590840000000" Dst="0" />
<file name="en-GB.tpl_bluestork.sys.ini" server="I:/auction-ruseasons/" local="130476590831126000" remote="130476590840000000" Dst="0" />
<file name="en-GB.tpl_hathor.ini" server="I:/auction-ruseasons/" local="130476590831136000" remote="130476590840000000" Dst="0" />
<file name="en-GB.tpl_hathor.sys.ini" server="I:/auction-ruseasons/" local="130476590831146000" remote="130476590840000000" Dst="0" />
<file name="en-GB.xml" server="I:/auction-ruseasons/" local="130419717481300000" remote="130419717500000000" Dst="0" />
<file name="index.html" server="I:/auction-ruseasons/" local="130419717481300000" remote="130419717500000000" Dst="0" />
</dwsync>