<?xml version="1.0" encoding="utf-8" ?>
<dwsync>
<file name="bids.php" server="I:/auction-ruseasons/" local="130477597773560000" remote="130477597780000000" Dst="0" />
<file name="bids.xml" server="I:/auction-ruseasons/" local="130477597773600000" remote="130477597780000000" Dst="0" />
<file name="data.php" server="I:/auction-ruseasons/" local="130477597773640000" remote="130477597780000000" Dst="0" />
<file name="data.xml" server="I:/auction-ruseasons/" local="130477597773690000" remote="130477597780000000" Dst="0" />
<file name="favorites.php" server="I:/auction-ruseasons/" local="130477597773780000" remote="130477597780000000" Dst="0" />
<file name="favorites.xml" server="I:/auction-ruseasons/" local="130477597774040000" remote="130477597780000000" Dst="0" />
<file name="lots.php" server="I:/auction-ruseasons/" local="130477597774090000" remote="130477597780000000" Dst="0" />
<file name="lots.xml" server="I:/auction-ruseasons/" local="130477597774190000" remote="130477597780000000" Dst="0" />
<file name="purchases.php" server="I:/auction-ruseasons/" local="130477597773560000" remote="130477597780000000" Dst="0" />
<file name="purchases.xml" server="I:/auction-ruseasons/" local="130478236043890000" remote="130478236060000000" Dst="0" />
<file name="bids.php" server="77.222.40.220//2013/public_html/" local="130516190632160000" remote="130519776600000000" Dst="0" />
<file name="bids.xml" server="77.222.40.220//2013/public_html/" local="130516190632200000" remote="130519776600000000" Dst="0" />
<file name="data.php" server="77.222.40.220//2013/public_html/" local="130516190632230000" remote="130519776600000000" Dst="0" />
<file name="data.xml" server="77.222.40.220//2013/public_html/" local="130516190632270000" remote="130519776600000000" Dst="0" />
<file name="favorites.php" server="77.222.40.220//2013/public_html/" local="130516190632420000" remote="130519776600000000" Dst="0" />
<file name="favorites.xml" server="77.222.40.220//2013/public_html/" local="130516190632450000" remote="130519776600000000" Dst="0" />
<file name="filters.php" server="77.222.40.220//2013/public_html/" local="130516190632460000" remote="130519776600000000" Dst="0" />
<file name="lots.php" server="77.222.40.220//2013/public_html/" local="130516190632490000" remote="130519776600000000" Dst="0" />
<file name="lots.xml" server="77.222.40.220//2013/public_html/" local="130516190632530000" remote="130519776600000000" Dst="0" />
<file name="purchases.php" server="77.222.40.220//2013/public_html/" local="130516190632540000" remote="130519776600000000" Dst="0" />
<file name="purchases.xml" server="77.222.40.220//2013/public_html/" local="130516190632570000" remote="130519776600000000" Dst="0" />
</dwsync>